tfjsa/__init__.py
tfjsa/gui.py
tfjsa/run.py
tfjsa/static/bootstrap.css
tfjsa/static/bootstrap.js
tfjsa/static/font-awesome.css
tfjsa/static/jquery-3.3.1.min.js
tfjsa/static/jquery.blockUI.js
tfjsa/static/jquery.form.min.js
tfjsa/static/popper.min.js
tfjsa/static/sample.csv
tfjsa/static/tf.min.js
tfjsa/static/webcam.js
tfjsa/static/Mobilenet/cat.jpg
tfjsa/static/Mobilenet/imagenet_classes.js
tfjsa/static/Mobilenet/mobilenet_2_5_224_tf.h5
tfjsa/static/Mobilenet/model.json
tfjsa/static/Mobilenet/shards/group1-shard1of1.bin
tfjsa/static/Mobilenet/shards/group10-shard1of1.bin
tfjsa/static/Mobilenet/shards/group11-shard1of1.bin
tfjsa/static/Mobilenet/shards/group12-shard1of1.bin
tfjsa/static/Mobilenet/shards/group13-shard1of1.bin
tfjsa/static/Mobilenet/shards/group14-shard1of1.bin
tfjsa/static/Mobilenet/shards/group15-shard1of1.bin
tfjsa/static/Mobilenet/shards/group16-shard1of1.bin
tfjsa/static/Mobilenet/shards/group17-shard1of1.bin
tfjsa/static/Mobilenet/shards/group18-shard1of1.bin
tfjsa/static/Mobilenet/shards/group19-shard1of1.bin
tfjsa/static/Mobilenet/shards/group2-shard1of1.bin
tfjsa/static/Mobilenet/shards/group20-shard1of1.bin
tfjsa/static/Mobilenet/shards/group21-shard1of1.bin
tfjsa/static/Mobilenet/shards/group22-shard1of1.bin
tfjsa/static/Mobilenet/shards/group23-shard1of1.bin
tfjsa/static/Mobilenet/shards/group24-shard1of1.bin
tfjsa/static/Mobilenet/shards/group25-shard1of1.bin
tfjsa/static/Mobilenet/shards/group26-shard1of1.bin
tfjsa/static/Mobilenet/shards/group27-shard1of1.bin
tfjsa/static/Mobilenet/shards/group28-shard1of1.bin
tfjsa/static/Mobilenet/shards/group29-shard1of1.bin
tfjsa/static/Mobilenet/shards/group3-shard1of1.bin
tfjsa/static/Mobilenet/shards/group30-shard1of1.bin
tfjsa/static/Mobilenet/shards/group31-shard1of1.bin
tfjsa/static/Mobilenet/shards/group32-shard1of1.bin
tfjsa/static/Mobilenet/shards/group33-shard1of1.bin
tfjsa/static/Mobilenet/shards/group34-shard1of1.bin
tfjsa/static/Mobilenet/shards/group35-shard1of1.bin
tfjsa-0.0.4.dist-info/LICENCE
tfjsa-0.0.4.dist-info/METADATA
tfjsa-0.0.4.dist-info/WHEEL
tfjsa-0.0.4.dist-info/top_level.txt
tfjsa-0.0.4.dist-info/RECORD
