Metadata-Version: 2.1
Name: tfjsa
Version: 0.0.4
Summary: tfjs(Tensorflow js)-based Flask web apps.
Home-page: http://pypi.python.org/pypi/tfjsa/
Author: Zhang
Author-email: oo@zju.edu.cn
License: LICENSE
License-File: LICENCE
Requires-Dist: flask
